tests/conftest.py
tests/test_calculators.py
tests/test_infra.py
tests/test_metrics.py
tests/test_trustifai.py
tests/test_visualizer.py
trustifai/__init__.py
trustifai/config.py
trustifai/core.py
trustifai/services.py
trustifai/structures.py
trustifai/visualizer.py
trustifai/metrics/__init__.py
trustifai/metrics/base.py
trustifai/metrics/calculators.py
trustifai/metrics/offline_metrics.py
trustifai/metrics/online_metrics.py
trustifai-0.1.5.dist-info/LICENSE
trustifai-0.1.5.dist-info/METADATA
trustifai-0.1.5.dist-info/WHEEL
trustifai-0.1.5.dist-info/top_level.txt
trustifai-0.1.5.dist-info/RECORD
