Metadata-Version: 2.1
Name: trustifai
Version: 0.1.5
Summary: Trustifai: A Comprehensive Framework for AI Trustworthiness
Author: Aaryan Verma
License: MIT
Project-URL: Homepage, https://github.com/Aaryanverma/trustifai
Classifier: License :: OSI Approved :: MIT License
Classifier: Programming Language :: Python :: 3
Classifier: Programming Language :: Python :: 3.10
Classifier: Programming Language :: Python :: 3.11
Classifier: Programming Language :: Python :: 3.12
Classifier: Programming Language :: Python :: 3.13
Requires-Python: >=3.10
License-File: LICENSE
Requires-Dist: ipython==8.12.3
Requires-Dist: litellm==1.81.4
Requires-Dist: nest-asyncio==1.6.0
Requires-Dist: nltk==3.9.1
Requires-Dist: numpy
Requires-Dist: pydantic==2.12.5
Requires-Dist: python-dotenv==1.2.1
Requires-Dist: pyvis==0.3.2
Requires-Dist: PyYAML==6.0.3
Requires-Dist: tenacity==8.2.3
Provides-Extra: test
Requires-Dist: pytest==8.3.4; extra == "test"
Requires-Dist: langchain-core==1.2.6; extra == "test"
Requires-Dist: llama-index==0.14.13; extra == "test"
Provides-Extra: trace
Requires-Dist: mlflow==3.8.1; extra == "trace"
